odoo/addons/statechart/README.rst
odoo/addons/statechart/__init__.py
odoo/addons/statechart/__manifest__.py
odoo/addons/statechart/exceptions.py
odoo/addons/statechart/i18n/fr.po
odoo/addons/statechart/i18n/statechart.pot
odoo/addons/statechart/models/__init__.py
odoo/addons/statechart/models/event.py
odoo/addons/statechart/models/interpreter.py
odoo/addons/statechart/models/statechart.py
odoo/addons/statechart/models/statechart_mixin.py
odoo/addons/statechart/readme/DESCRIPTION.md
odoo/addons/statechart/readme/USAGE.md
odoo/addons/statechart/static/description/icon.png
odoo/addons/statechart/static/description/index.html
odoo/addons/statechart/static/src/core/errors/error_dialogs.esm.js
odoo_addon_statechart-18.0.1.0.0.4.dist-info/METADATA
odoo_addon_statechart-18.0.1.0.0.4.dist-info/WHEEL
odoo_addon_statechart-18.0.1.0.0.4.dist-info/top_level.txt
odoo_addon_statechart-18.0.1.0.0.4.dist-info/RECORD
