Metadata-Version: 2.1
Name: odoo-addon-statechart
Version: 18.0.1.0.0.4
Requires-Python: >=3.10
Requires-Dist: odoo==18.0.*
Requires-Dist: sismic>=1.4.1
Summary: Add Statecharts to Odoo models
Home-page: https://github.com/acsone/scobidoo
License: LGPL-3
Author: ACSONE SA/NV,Odoo Community Association (OCA)
Author-email: support@odoo-community.org
Classifier: Programming Language :: Python
Classifier: Framework :: Odoo
Classifier: Framework :: Odoo :: 18.0
Classifier: License :: OSI Approved :: GNU Lesser General Public License v3 (LGPLv3)
